georges/__init__.py
georges/fermi/.mypy_cache/.gitignore
georges/fermi/.mypy_cache/3.10/@plugins_snapshot.json
georges/fermi/.mypy_cache/3.10/__future__.data.json
georges/fermi/.mypy_cache/3.10/__future__.meta.json
georges/fermi/.mypy_cache/3.10/_ast.data.json
georges/fermi/.mypy_cache/3.10/_ast.meta.json
georges/fermi/.mypy_cache/3.10/_bisect.data.json
georges/fermi/.mypy_cache/3.10/_bisect.meta.json
georges/fermi/.mypy_cache/3.10/_codecs.data.json
georges/fermi/.mypy_cache/3.10/_codecs.meta.json
georges/fermi/.mypy_cache/3.10/_collections_abc.data.json
georges/fermi/.mypy_cache/3.10/_collections_abc.meta.json
georges/fermi/.mypy_cache/3.10/_ctypes.data.json
georges/fermi/.mypy_cache/3.10/_ctypes.meta.json
georges/fermi/.mypy_cache/3.10/_decimal.data.json
georges/fermi/.mypy_cache/3.10/_decimal.meta.json
georges/fermi/.mypy_cache/3.10/_operator.data.json
georges/fermi/.mypy_cache/3.10/_operator.meta.json
georges/fermi/.mypy_cache/3.10/_thread.data.json
georges/fermi/.mypy_cache/3.10/_thread.meta.json
georges/fermi/.mypy_cache/3.10/_typeshed/__init__.data.json
georges/fermi/.mypy_cache/3.10/_typeshed/__init__.meta.json
georges/fermi/.mypy_cache/3.10/_warnings.data.json
georges/fermi/.mypy_cache/3.10/_warnings.meta.json
georges/fermi/.mypy_cache/3.10/_weakref.data.json
georges/fermi/.mypy_cache/3.10/_weakref.meta.json
georges/fermi/.mypy_cache/3.10/_weakrefset.data.json
georges/fermi/.mypy_cache/3.10/_weakrefset.meta.json
georges/fermi/.mypy_cache/3.10/abc.data.json
georges/fermi/.mypy_cache/3.10/abc.meta.json
georges/fermi/.mypy_cache/3.10/array.data.json
georges/fermi/.mypy_cache/3.10/array.meta.json
georges/fermi/.mypy_cache/3.10/ast.data.json
georges/fermi/.mypy_cache/3.10/ast.meta.json
georges/fermi/.mypy_cache/3.10/babel/__init__.data.json
georges/fermi/.mypy_cache/3.10/babel/__init__.meta.json
georges/fermi/.mypy_cache/3.10/babel/core.data.json
georges/fermi/.mypy_cache/3.10/babel/core.meta.json
georges/fermi/.mypy_cache/3.10/babel/localedata.data.json
georges-2024.2.dist-info/LICENSE
georges-2024.2.dist-info/METADATA
georges-2024.2.dist-info/WHEEL
georges-2024.2.dist-info/RECORD
